{
  "name": "research-portfolio",
  "build": {
    "dockerfile": "Dockerfile"
  },
  "features": {
    "ghcr.io/devcontainers/features/github-cli:1": {},
    "ghcr.io/devcontainers/features/docker-outside-of-docker:1": {}
  },
  "forwardPorts": [5173],
  "postCreateCommand": "bash .devcontainer/post-create.sh",
  "customizations": {
    "vscode": {
      "extensions": [
        "dbaeumer.vscode-eslint",
        "esbenp.prettier-vscode",
        "eamodio.gitlens"
      ]
    }
  },
  "remoteUser": "node"
}
